uda/__init__.py
uda-2.9.1.dist-info/METADATA
uda-2.9.1.dist-info/WHEEL
uda-2.9.1.dist-info/top_level.txt
uda-2.9.1.dist-info/RECORD
