Metadata-Version: 2.4
Name: uda
Version: 2.9.1
Summary: Universal Data Access (UDA)
License: Apache-2.0 license
Project-URL: homepage, https://ukaea.github.io/UDA/
Project-URL: documentation, https://ukaea.github.io/UDA/
Project-URL: source, https://github.com/ukaea/UDA
Project-URL: tracker, https://github.com/ukaea/UDA/issues
Keywords: deprecated
Classifier: Intended Audience :: Science/Research
Classifier: Programming Language :: C
Classifier: Programming Language :: Python :: 3
Classifier: Programming Language :: Python :: 3 :: Only
Classifier: Operating System :: POSIX :: Linux
Classifier: Operating System :: MacOS :: MacOS X
Classifier: Operating System :: Microsoft :: Windows
Requires-Python: >=3.5
Requires-Dist: pyuda
Provides-Extra: plot
Requires-Dist: pyplot; extra == "plot"
Provides-Extra: full
Requires-Dist: pyplot; extra == "full"
Requires-Dist: rich; extra == "full"
